odoo/addons/hr_holidays_calendar_name/README.rst
odoo/addons/hr_holidays_calendar_name/__init__.py
odoo/addons/hr_holidays_calendar_name/__manifest__.py
odoo/addons/hr_holidays_calendar_name/i18n/es.po
odoo/addons/hr_holidays_calendar_name/i18n/fr.po
odoo/addons/hr_holidays_calendar_name/i18n/hr_holidays_calendar_name.pot
odoo/addons/hr_holidays_calendar_name/i18n/it.po
odoo/addons/hr_holidays_calendar_name/models/__init__.py
odoo/addons/hr_holidays_calendar_name/models/hr_leave.py
odoo/addons/hr_holidays_calendar_name/models/hr_leave_type.py
odoo/addons/hr_holidays_calendar_name/readme/CONTRIBUTORS.rst
odoo/addons/hr_holidays_calendar_name/readme/DESCRIPTION.rst
odoo/addons/hr_holidays_calendar_name/static/description/icon.png
odoo/addons/hr_holidays_calendar_name/static/description/index.html
odoo/addons/hr_holidays_calendar_name/tests/__init__.py
odoo/addons/hr_holidays_calendar_name/tests/test_hr_leave.py
odoo/addons/hr_holidays_calendar_name/views/hr_leave_type.xml
odoo14_addon_hr_holidays_calendar_name-14.0.1.0.1.dev5.dist-info/METADATA
odoo14_addon_hr_holidays_calendar_name-14.0.1.0.1.dev5.dist-info/WHEEL
odoo14_addon_hr_holidays_calendar_name-14.0.1.0.1.dev5.dist-info/top_level.txt
odoo14_addon_hr_holidays_calendar_name-14.0.1.0.1.dev5.dist-info/RECORD
